clmm/__init__.py
clmm/clusterensemble.py
clmm/galaxycluster.py
clmm/gcdata.py
clmm/cosmology/__init__.py
clmm/cosmology/ccl.py
clmm/cosmology/cluster_toolkit.py
clmm/cosmology/numcosmo.py
clmm/cosmology/parent_class.py
clmm/dataops/__init__.py
clmm/support/__init__.py
clmm/support/mock_data.py
clmm/support/sampler.py
clmm/theory/__init__.py
clmm/theory/ccl.py
clmm/theory/cluster_toolkit.py
clmm/theory/func_layer.py
clmm/theory/generic.py
clmm/theory/miscentering.py
clmm/theory/numcosmo.py
clmm/theory/parent_class.py
clmm/utils/__init__.py
clmm/utils/beta_lens.py
clmm/utils/boost.py
clmm/utils/constants.py
clmm/utils/ellipticity.py
clmm/utils/plotting.py
clmm/utils/redshift_distributions.py
clmm/utils/redshift_tools.py
clmm/utils/statistic.py
clmm/utils/units.py
clmm/utils/validation.py
clmm-1.16.10.dist-info/METADATA
clmm-1.16.10.dist-info/WHEEL
clmm-1.16.10.dist-info/licenses/LICENSE
clmm-1.16.10.dist-info/RECORD
