Metadata-Version: 2.4
Name: clmm
Version: 1.16.10
Summary: A comprehensive package for galaxy cluster weak lensing
Project-URL: Repository, https://github.com/LSSTDESC/CLMM
Author: The LSST DESC CLMM Contributors
License-Expression: BSD-3-Clause
License-File: LICENSE
Classifier: Development Status :: 4 - Beta
Classifier: Intended Audience :: Developers
Classifier: Intended Audience :: Science/Research
Classifier: License :: OSI Approved :: BSD License
Classifier: Operating System :: OS Independent
Classifier: Programming Language :: Python
Requires-Python: >=3.8
Requires-Dist: astropy!=5.0,>=4
Requires-Dist: healpy
Requires-Dist: matplotlib
Requires-Dist: numpy>=2.0
Requires-Dist: qp-prob
Requires-Dist: scipy>=1.6
